lab1/collatz.sv
module collatz( input logic         clk,   // Clock
		input logic 	    go,    // Load value from n; start iterating
		input logic  [31:0] n,     // Start value; only read when go = 1
		output logic [31:0] dout,  // Iteration value: true after go = 1
		output logic 	    done); // True when dout reaches 1

   always_ff @(posedge clk) begin
	   if (dout == 32'd2) done <= 1'b1;
	   if (go) begin 
		   dout <= n;
		   done <= 1'b0;
	   end
	   else if (done);
	   else if(dout[0])	dout <= (dout * 3) + 1;
	   else			dout <= dout >> 1;
   end
endmodule

lab1/range.sv
module range
   #(parameter
     RAM_WORDS = 16,            // Number of counts to store in RAM
     RAM_ADDR_BITS = 4)         // Number of RAM address bits
   (input logic         clk,    // Clock
    input logic 	go,     // Read start and start testing
    input logic [31:0] 	start,  // Number to start from or count to read
    output logic 	done,   // True once memory is filled
    output logic [15:0] count); // Iteration count once finished

   logic 		cgo;    // "go" for the Collatz iterator
   logic                cdone;  // "done" from the Collatz iterator
   logic [31:0] 	n;      // number to start the Collatz iterator

// verilator lint_off PINCONNECTEMPTY
   
   // Instantiate the Collatz iterator
   collatz c1(.clk(clk),
	      .go(cgo),
	      .n(n),
	      .done(cdone),
	      .dout());

   logic [RAM_ADDR_BITS - 1:0] 	 num;         // The RAM address to write
   logic 			 running = 0; // True during the iterations

   /* Replace this comment and the code below with your solution,
      which should generate running, done, cgo, n, num, we, and din */

     	always_ff @(posedge clk) begin
		if (~running) done <= 0;
		if (go) begin 
			running <= 1;
			n <= start;
			num <= 0;
			din <= 1;
			cgo <= 1;
		end
		if (cgo) begin
			cgo <= 0;
			din <= 1;
		end
		if (we) begin
		   we <= 0;
		   n <= n + 1;
		   num <= num + 1;
		   if (num == 4'hf) begin
			   running <= 0;
			   done <= 1;
		   end
		end
		else if (cdone) begin
			we <= 1;
			cgo <= 1;
		end
		else if (running && ~cgo) din <= din + 1;
	end
/* Replace this comment and the code above with your solution. */

   logic 			 we;                    // Write din to addr
   logic [15:0] 		 din;                   // Data to write
   logic [15:0] 		 mem[RAM_WORDS - 1:0];  // The RAM itself
   logic [RAM_ADDR_BITS - 1:0] 	 addr;                  // Address to read/write

   assign addr = we ? num : start[RAM_ADDR_BITS-1:0];
   
   always_ff @(posedge clk) begin
      if (we) mem[addr] <= din;
      count <= mem[addr];      
   end

endmodule

lab1/range.vcd
$version Generated by VerilatedVcd $end
$date Tue Feb 10 20:46:47 2026
 $end
$timescale   1ns $end

 $scope module TOP $end
  $var wire  1 /" clk $end
  $var wire 16 O" count [15:0] $end
  $var wire  1 G" done $end
  $var wire  1 7" go $end
  $var wire 32 ?" start [31:0] $end
  $scope module range $end
   $var wire 32 _" RAM_ADDR_BITS [31:0] $end
   $var wire 32 W" RAM_WORDS [31:0] $end
   $var wire  4 + addr [3:0] $end
   $var wire  1 ; cdone $end
   $var wire  1 3 cgo $end
   $var wire  1 /" clk $end
   $var wire 16 O" count [15:0] $end
   $var wire 16 [ din [15:0] $end
   $var wire  1 G" done $end
   $var wire  1 7" go $end
   $var wire 16 c mem(0) [15:0] $end
   $var wire 16 d mem(1) [15:0] $end
   $var wire 16 m mem(10) [15:0] $end
   $var wire 16 n mem(11) [15:0] $end
   $var wire 16 o mem(12) [15:0] $end
   $var wire 16 p mem(13) [15:0] $end
   $var wire 16 q mem(14) [15:0] $end
   $var wire 16 r mem(15) [15:0] $end
   $var wire 16 e mem(2) [15:0] $end
   $var wire 16 f mem(3) [15:0] $end
   $var wire 16 g mem(4) [15:0] $end
   $var wire 16 h mem(5) [15:0] $end
   $var wire 16 i mem(6) [15:0] $end
   $var wire 16 j mem(7) [15:0] $end
   $var wire 16 k mem(8) [15:0] $end
   $var wire 16 l mem(9) [15:0] $end
   $var wire 32 C n [31:0] $end
   $var wire  4 K num [3:0] $end
   $var wire  1 # running $end
   $var wire 32 ?" start [31:0] $end
   $var wire  1 S we $end
   $scope module c1 $end
    $var wire  1 /" clk $end
    $var wire  1 ; done $end
    $var wire 32 '" dout [31:0] $end
    $var wire  1 3 go $end
    $var wire 32 C n [31:0] $end
   $upscope $end
  $upscope $end
 $upscope $end
$enddefinitions $end


#0
0#
b0111 +
03
0;
b00000000000000000000000000000000 C
b0000 K
0S
b0000000000000000 [
b0000000000000000 c
b0000000000000000 d
b0000000000000000 e
b0000000000000000 f
b0000000000000000 g
b0000000000000000 h
b0000000000000000 i
b0000000000000000 j
b0000000000000000 k
b0000000000000000 l
b0000000000000000 m
b0000000000000000 n
b0000000000000000 o
b0000000000000000 p
b0000000000000000 q
b0000000000000000 r
b00000000000000000000000000000000 '"
0/"
17"
b00000000000000000000000000000111 ?"
0G"
b0000000000000000 O"
b00000000000000000000000000010000 W"
b00000000000000000000000000000100 _"
#10
1#
13
b00000000000000000000000000000111 C
b0000000000000001 [
1/"
#20
0/"
#30
03
b00000000000000000000000000000111 '"
1/"
#40
0/"
07"
#50
b0000000000000010 [
b00000000000000000000000000010110 '"
1/"
#60
0/"
#70
b0000000000000011 [
b00000000000000000000000000001011 '"
1/"
#80
0/"
#90
b0000000000000100 [
b00000000000000000000000000100010 '"
1/"
#100
0/"
#110
b0000000000000101 [
b00000000000000000000000000010001 '"
1/"
#120
0/"
#130
b0000000000000110 [
b00000000000000000000000000110100 '"
1/"
#140
0/"
#150
b0000000000000111 [
b00000000000000000000000000011010 '"
1/"
#160
0/"
#170
b0000000000001000 [
b00000000000000000000000000001101 '"
1/"
#180
0/"
#190
b0000000000001001 [
b00000000000000000000000000101000 '"
1/"
#200
0/"
#210
b0000000000001010 [
b00000000000000000000000000010100 '"
1/"
#220
0/"
#230
b0000000000001011 [
b00000000000000000000000000001010 '"
1/"
#240
0/"
#250
b0000000000001100 [
b00000000000000000000000000000101 '"
1/"
#260
0/"
#270
b0000000000001101 [
b00000000000000000000000000010000 '"
1/"
#280
0/"
#290
b0000000000001110 [
b00000000000000000000000000001000 '"
1/"
#300
0/"
#310
b0000000000001111 [
b00000000000000000000000000000100 '"
1/"
#320
0/"
#330
b0000000000010000 [
b00000000000000000000000000000010 '"
1/"
#340
0/"
#350
1;
b0000000000010001 [
b00000000000000000000000000000001 '"
1/"
#360
0/"
#370
b0000 +
13
1S
1/"
#380
0/"
#390
b0111 +
03
0;
b00000000000000000000000000001000 C
b0001 K
0S
b0000000000000001 [
b0000000000010001 c
b00000000000000000000000000000111 '"
1/"
#400
0/"
#410
b0000000000000010 [
b00000000000000000000000000010110 '"
1/"
#420
0/"
#430
b0000000000000011 [
b00000000000000000000000000001011 '"
1/"
#440
0/"
#450
b0000000000000100 [
b00000000000000000000000000100010 '"
1/"
#460
0/"
#470
b0000000000000101 [
b00000000000000000000000000010001 '"
1/"
#480
0/"
#490
b0000000000000110 [
b00000000000000000000000000110100 '"
1/"
#500
0/"
#510
b0000000000000111 [
b00000000000000000000000000011010 '"
1/"
#520
0/"
#530
b0000000000001000 [
b00000000000000000000000000001101 '"
1/"
#540
0/"
#550
b0000000000001001 [
b00000000000000000000000000101000 '"
1/"
#560
0/"
#570
b0000000000001010 [
b00000000000000000000000000010100 '"
1/"
#580
0/"
#590
b0000000000001011 [
b00000000000000000000000000001010 '"
1/"
#600
0/"
#610
b0000000000001100 [
b00000000000000000000000000000101 '"
1/"
#620
0/"
#630
b0000000000001101 [
b00000000000000000000000000010000 '"
1/"
#640
0/"
#650
b0000000000001110 [
b00000000000000000000000000001000 '"
1/"
#660
0/"
#670
b0000000000001111 [
b00000000000000000000000000000100 '"
1/"
#680
0/"
#690
b0000000000010000 [
b00000000000000000000000000000010 '"
1/"
#700
0/"
#710
1;
b0000000000010001 [
b00000000000000000000000000000001 '"
1/"
#720
0/"
#730
b0001 +
13
1S
1/"
#740
0/"
#750
b0111 +
03
0;
b00000000000000000000000000001001 C
b0010 K
0S
b0000000000000001 [
b0000000000010001 d
b00000000000000000000000000001000 '"
1/"
#760
0/"
#770
b0000000000000010 [
b00000000000000000000000000000100 '"
1/"
#780
0/"
#790
b0000000000000011 [
b00000000000000000000000000000010 '"
1/"
#800
0/"
#810
1;
b0000000000000100 [
b00000000000000000000000000000001 '"
1/"
#820
0/"
#830
b0010 +
13
1S
1/"
#840
0/"
#850
b0111 +
03
0;
b00000000000000000000000000001010 C
b0011 K
0S
b0000000000000001 [
b0000000000000100 e
b00000000000000000000000000001001 '"
1/"
#860
0/"
#870
b0000000000000010 [
b00000000000000000000000000011100 '"
1/"
#880
0/"
#890
b0000000000000011 [
b00000000000000000000000000001110 '"
1/"
#900
0/"
#910
b0000000000000100 [
b00000000000000000000000000000111 '"
1/"
#920
0/"
#930
b0000000000000101 [
b00000000000000000000000000010110 '"
1/"
#940
0/"
#950
b0000000000000110 [
b00000000000000000000000000001011 '"
1/"
#960
0/"
#970
b0000000000000111 [
b00000000000000000000000000100010 '"
1/"
#980
0/"
#990
b0000000000001000 [
b00000000000000000000000000010001 '"
1/"
#1000
0/"
#1010
b0000000000001001 [
b00000000000000000000000000110100 '"
1/"
#1020
0/"
#1030
b0000000000001010 [
b00000000000000000000000000011010 '"
1/"
#1040
0/"
#1050
b0000000000001011 [
b00000000000000000000000000001101 '"
1/"
#1060
0/"
#1070
b0000000000001100 [
b00000000000000000000000000101000 '"
1/"
#1080
0/"
#1090
b0000000000001101 [
b00000000000000000000000000010100 '"
1/"
#1100
0/"
#1110
b0000000000001110 [
b00000000000000000000000000001010 '"
1/"
#1120
0/"
#1130
b0000000000001111 [
b00000000000000000000000000000101 '"
1/"
#1140
0/"
#1150
b0000000000010000 [
b00000000000000000000000000010000 '"
1/"
#1160
0/"
#1170
b0000000000010001 [
b00000000000000000000000000001000 '"
1/"
#1180
0/"
#1190
b0000000000010010 [
b00000000000000000000000000000100 '"
1/"
#1200
0/"
#1210
b0000000000010011 [
b00000000000000000000000000000010 '"
1/"
#1220
0/"
#1230
1;
b0000000000010100 [
b00000000000000000000000000000001 '"
1/"
#1240
0/"
#1250
b0011 +
13
1S
1/"
#1260
0/"
#1270
b0111 +
03
0;
b00000000000000000000000000001011 C
b0100 K
0S
b0000000000000001 [
b0000000000010100 f
b00000000000000000000000000001010 '"
1/"
#1280
0/"
#1290
b0000000000000010 [
b00000000000000000000000000000101 '"
1/"
#1300
0/"
#1310
b0000000000000011 [
b00000000000000000000000000010000 '"
1/"
#1320
0/"
#1330
b0000000000000100 [
b00000000000000000000000000001000 '"
1/"
#1340
0/"
#1350
b0000000000000101 [
b00000000000000000000000000000100 '"
1/"
#1360
0/"
#1370
b0000000000000110 [
b00000000000000000000000000000010 '"
1/"
#1380
0/"
#1390
1;
b0000000000000111 [
b00000000000000000000000000000001 '"
1/"
#1400
0/"
#1410
b0100 +
13
1S
1/"
#1420
0/"
#1430
b0111 +
03
0;
b00000000000000000000000000001100 C
b0101 K
0S
b0000000000000001 [
b0000000000000111 g
b00000000000000000000000000001011 '"
1/"
#1440
0/"
#1450
b0000000000000010 [
b00000000000000000000000000100010 '"
1/"
#1460
0/"
#1470
b0000000000000011 [
b00000000000000000000000000010001 '"
1/"
#1480
0/"
#1490
b0000000000000100 [
b00000000000000000000000000110100 '"
1/"
#1500
0/"
#1510
b0000000000000101 [
b00000000000000000000000000011010 '"
1/"
#1520
0/"
#1530
b0000000000000110 [
b00000000000000000000000000001101 '"
1/"
#1540
0/"
#1550
b0000000000000111 [
b00000000000000000000000000101000 '"
1/"
#1560
0/"
#1570
b0000000000001000 [
b00000000000000000000000000010100 '"
1/"
#1580
0/"
#1590
b0000000000001001 [
b00000000000000000000000000001010 '"
1/"
#1600
0/"
#1610
b0000000000001010 [
b00000000000000000000000000000101 '"
1/"
#1620
0/"
#1630
b0000000000001011 [
b00000000000000000000000000010000 '"
1/"
#1640
0/"
#1650
b0000000000001100 [
b00000000000000000000000000001000 '"
1/"
#1660
0/"
#1670
b0000000000001101 [
b00000000000000000000000000000100 '"
1/"
#1680
0/"
#1690
b0000000000001110 [
b00000000000000000000000000000010 '"
1/"
#1700
0/"
#1710
1;
b0000000000001111 [
b00000000000000000000000000000001 '"
1/"
#1720
0/"
#1730
b0101 +
13
1S
1/"
#1740
0/"
#1750
b0111 +
03
0;
b00000000000000000000000000001101 C
b0110 K
0S
b0000000000000001 [
b0000000000001111 h
b00000000000000000000000000001100 '"
1/"
#1760
0/"
#1770
b0000000000000010 [
b00000000000000000000000000000110 '"
1/"
#1780
0/"
#1790
b0000000000000011 [
b00000000000000000000000000000011 '"
1/"
#1800
0/"
#1810
b0000000000000100 [
b00000000000000000000000000001010 '"
1/"
#1820
0/"
#1830
b0000000000000101 [
b00000000000000000000000000000101 '"
1/"
#1840
0/"
#1850
b0000000000000110 [
b00000000000000000000000000010000 '"
1/"
#1860
0/"
#1870
b0000000000000111 [
b00000000000000000000000000001000 '"
1/"
#1880
0/"
#1890
b0000000000001000 [
b00000000000000000000000000000100 '"
1/"
#1900
0/"
#1910
b0000000000001001 [
b00000000000000000000000000000010 '"
1/"
#1920
0/"
#1930
1;
b0000000000001010 [
b00000000000000000000000000000001 '"
1/"
#1940
0/"
#1950
b0110 +
13
1S
1/"
#1960
0/"
#1970
b0111 +
03
0;
b00000000000000000000000000001110 C
b0111 K
0S
b0000000000000001 [
b0000000000001010 i
b00000000000000000000000000001101 '"
1/"
#1980
0/"
#1990
b0000000000000010 [
b00000000000000000000000000101000 '"
1/"
#2000
0/"
#2010
b0000000000000011 [
b00000000000000000000000000010100 '"
1/"
#2020
0/"
#2030
b0000000000000100 [
b00000000000000000000000000001010 '"
1/"
#2040
0/"
#2050
b0000000000000101 [
b00000000000000000000000000000101 '"
1/"
#2060
0/"
#2070
b0000000000000110 [
b00000000000000000000000000010000 '"
1/"
#2080
0/"
#2090
b0000000000000111 [
b00000000000000000000000000001000 '"
1/"
#2100
0/"
#2110
b0000000000001000 [
b00000000000000000000000000000100 '"
1/"
#2120
0/"
#2130
b0000000000001001 [
b00000000000000000000000000000010 '"
1/"
#2140
0/"
#2150
1;
b0000000000001010 [
b00000000000000000000000000000001 '"
1/"
#2160
0/"
#2170
13
1S
1/"
#2180
0/"
#2190
03
0;
b00000000000000000000000000001111 C
b1000 K
0S
b0000000000000001 [
b0000000000001010 j
b00000000000000000000000000001110 '"
1/"
#2200
0/"
#2210
b0000000000000010 [
b00000000000000000000000000000111 '"
1/"
b0000000000001010 O"
#2220
0/"
#2230
b0000000000000011 [
b00000000000000000000000000010110 '"
1/"
#2240
0/"
#2250
b0000000000000100 [
b00000000000000000000000000001011 '"
1/"
#2260
0/"
#2270
b0000000000000101 [
b00000000000000000000000000100010 '"
1/"
#2280
0/"
#2290
b0000000000000110 [
b00000000000000000000000000010001 '"
1/"
#2300
0/"
#2310
b0000000000000111 [
b00000000000000000000000000110100 '"
1/"
#2320
0/"
#2330
b0000000000001000 [
b00000000000000000000000000011010 '"
1/"
#2340
0/"
#2350
b0000000000001001 [
b00000000000000000000000000001101 '"
1/"
#2360
0/"
#2370
b0000000000001010 [
b00000000000000000000000000101000 '"
1/"
#2380
0/"
#2390
b0000000000001011 [
b00000000000000000000000000010100 '"
1/"
#2400
0/"
#2410
b0000000000001100 [
b00000000000000000000000000001010 '"
1/"
#2420
0/"
#2430
b0000000000001101 [
b00000000000000000000000000000101 '"
1/"
#2440
0/"
#2450
b0000000000001110 [
b00000000000000000000000000010000 '"
1/"
#2460
0/"
#2470
b0000000000001111 [
b00000000000000000000000000001000 '"
1/"
#2480
0/"
#2490
b0000000000010000 [
b00000000000000000000000000000100 '"
1/"
#2500
0/"
#2510
b0000000000010001 [
b00000000000000000000000000000010 '"
1/"
#2520
0/"
#2530
1;
b0000000000010010 [
b00000000000000000000000000000001 '"
1/"
#2540
0/"
#2550
b1000 +
13
1S
1/"
#2560
0/"
#2570
b0111 +
03
0;
b00000000000000000000000000010000 C
b1001 K
0S
b0000000000000001 [
b0000000000010010 k
b00000000000000000000000000001111 '"
1/"
b0000000000000000 O"
#2580
0/"
#2590
b0000000000000010 [
b00000000000000000000000000101110 '"
1/"
b0000000000001010 O"
#2600
0/"
#2610
b0000000000000011 [
b00000000000000000000000000010111 '"
1/"
#2620
0/"
#2630
b0000000000000100 [
b00000000000000000000000001000110 '"
1/"
#2640
0/"
#2650
b0000000000000101 [
b00000000000000000000000000100011 '"
1/"
#2660
0/"
#2670
b0000000000000110 [
b00000000000000000000000001101010 '"
1/"
#2680
0/"
#2690
b0000000000000111 [
b00000000000000000000000000110101 '"
1/"
#2700
0/"
#2710
b0000000000001000 [
b00000000000000000000000010100000 '"
1/"
#2720
0/"
#2730
b0000000000001001 [
b00000000000000000000000001010000 '"
1/"
#2740
0/"
#2750
b0000000000001010 [
b00000000000000000000000000101000 '"
1/"
#2760
0/"
#2770
b0000000000001011 [
b00000000000000000000000000010100 '"
1/"
#2780
0/"
#2790
b0000000000001100 [
b00000000000000000000000000001010 '"
1/"
#2800
0/"
#2810
b0000000000001101 [
b00000000000000000000000000000101 '"
1/"
#2820
0/"
#2830
b0000000000001110 [
b00000000000000000000000000010000 '"
1/"
#2840
0/"
#2850
b0000000000001111 [
b00000000000000000000000000001000 '"
1/"
#2860
0/"
#2870
b0000000000010000 [
b00000000000000000000000000000100 '"
1/"
#2880
0/"
#2890
b0000000000010001 [
b00000000000000000000000000000010 '"
1/"
#2900
0/"
#2910
1;
b0000000000010010 [
b00000000000000000000000000000001 '"
1/"
#2920
0/"
#2930
b1001 +
13
1S
1/"
#2940
0/"
#2950
b0111 +
03
0;
b00000000000000000000000000010001 C
b1010 K
0S
b0000000000000001 [
b0000000000010010 l
b00000000000000000000000000010000 '"
1/"
b0000000000000000 O"
#2960
0/"
#2970
b0000000000000010 [
b00000000000000000000000000001000 '"
1/"
b0000000000001010 O"
#2980
0/"
#2990
b0000000000000011 [
b00000000000000000000000000000100 '"
1/"
#3000
0/"
#3010
b0000000000000100 [
b00000000000000000000000000000010 '"
1/"
#3020
0/"
#3030
1;
b0000000000000101 [
b00000000000000000000000000000001 '"
1/"
#3040
0/"
#3050
b1010 +
13
1S
1/"
#3060
0/"
#3070
b0111 +
03
0;
b00000000000000000000000000010010 C
b1011 K
0S
b0000000000000001 [
b0000000000000101 m
b00000000000000000000000000010001 '"
1/"
b0000000000000000 O"
#3080
0/"
#3090
b0000000000000010 [
b00000000000000000000000000110100 '"
1/"
b0000000000001010 O"
#3100
0/"
#3110
b0000000000000011 [
b00000000000000000000000000011010 '"
1/"
#3120
0/"
#3130
b0000000000000100 [
b00000000000000000000000000001101 '"
1/"
#3140
0/"
#3150
b0000000000000101 [
b00000000000000000000000000101000 '"
1/"
#3160
0/"
#3170
b0000000000000110 [
b00000000000000000000000000010100 '"
1/"
#3180
0/"
#3190
b0000000000000111 [
b00000000000000000000000000001010 '"
1/"
#3200
0/"
#3210
b0000000000001000 [
b00000000000000000000000000000101 '"
1/"
#3220
0/"
#3230
b0000000000001001 [
b00000000000000000000000000010000 '"
1/"
#3240
0/"
#3250
b0000000000001010 [
b00000000000000000000000000001000 '"
1/"
#3260
0/"
#3270
b0000000000001011 [
b00000000000000000000000000000100 '"
1/"
#3280
0/"
#3290
b0000000000001100 [
b00000000000000000000000000000010 '"
1/"
#3300
0/"
#3310
1;
b0000000000001101 [
b00000000000000000000000000000001 '"
1/"
#3320
0/"
#3330
b1011 +
13
1S
1/"
#3340
0/"
#3350
b0111 +
03
0;
b00000000000000000000000000010011 C
b1100 K
0S
b0000000000000001 [
b0000000000001101 n
b00000000000000000000000000010010 '"
1/"
b0000000000000000 O"
#3360
0/"
#3370
b0000000000000010 [
b00000000000000000000000000001001 '"
1/"
b0000000000001010 O"
#3380
0/"
#3390
b0000000000000011 [
b00000000000000000000000000011100 '"
1/"
#3400
0/"
#3410
b0000000000000100 [
b00000000000000000000000000001110 '"
1/"
#3420
0/"
#3430
b0000000000000101 [
b00000000000000000000000000000111 '"
1/"
#3440
0/"
#3450
b0000000000000110 [
b00000000000000000000000000010110 '"
1/"
#3460
0/"
#3470
b0000000000000111 [
b00000000000000000000000000001011 '"
1/"
#3480
0/"
#3490
b0000000000001000 [
b00000000000000000000000000100010 '"
1/"
#3500
0/"
#3510
b0000000000001001 [
b00000000000000000000000000010001 '"
1/"
#3520
0/"
#3530
b0000000000001010 [
b00000000000000000000000000110100 '"
1/"
#3540
0/"
#3550
b0000000000001011 [
b00000000000000000000000000011010 '"
1/"
#3560
0/"
#3570
b0000000000001100 [
b00000000000000000000000000001101 '"
1/"
#3580
0/"
#3590
b0000000000001101 [
b00000000000000000000000000101000 '"
1/"
#3600
0/"
#3610
b0000000000001110 [
b00000000000000000000000000010100 '"
1/"
#3620
0/"
#3630
b0000000000001111 [
b00000000000000000000000000001010 '"
1/"
#3640
0/"
#3650
b0000000000010000 [
b00000000000000000000000000000101 '"
1/"
#3660
0/"
#3670
b0000000000010001 [
b00000000000000000000000000010000 '"
1/"
#3680
0/"
#3690
b0000000000010010 [
b00000000000000000000000000001000 '"
1/"
#3700
0/"
#3710
b0000000000010011 [
b00000000000000000000000000000100 '"
1/"
#3720
0/"
#3730
b0000000000010100 [
b00000000000000000000000000000010 '"
1/"
#3740
0/"
#3750
1;
b0000000000010101 [
b00000000000000000000000000000001 '"
1/"
#3760
0/"
#3770
b1100 +
13
1S
1/"
#3780
0/"
#3790
b0111 +
03
0;
b00000000000000000000000000010100 C
b1101 K
0S
b0000000000000001 [
b0000000000010101 o
b00000000000000000000000000010011 '"
1/"
b0000000000000000 O"
#3800
0/"
#3810
b0000000000000010 [
b00000000000000000000000000111010 '"
1/"
b0000000000001010 O"
#3820
0/"
#3830
b0000000000000011 [
b00000000000000000000000000011101 '"
1/"
#3840
0/"
#3850
b0000000000000100 [
b00000000000000000000000001011000 '"
1/"
#3860
0/"
#3870
b0000000000000101 [
b00000000000000000000000000101100 '"
1/"
#3880
0/"
#3890
b0000000000000110 [
b00000000000000000000000000010110 '"
1/"
#3900
0/"
#3910
b0000000000000111 [
b00000000000000000000000000001011 '"
1/"
#3920
0/"
#3930
b0000000000001000 [
b00000000000000000000000000100010 '"
1/"
#3940
0/"
#3950
b0000000000001001 [
b00000000000000000000000000010001 '"
1/"
#3960
0/"
#3970
b0000000000001010 [
b00000000000000000000000000110100 '"
1/"
#3980
0/"
#3990
b0000000000001011 [
b00000000000000000000000000011010 '"
1/"
#4000
0/"
#4010
b0000000000001100 [
b00000000000000000000000000001101 '"
1/"
#4020
0/"
#4030
b0000000000001101 [
b00000000000000000000000000101000 '"
1/"
#4040
0/"
#4050
b0000000000001110 [
b00000000000000000000000000010100 '"
1/"
#4060
0/"
#4070
b0000000000001111 [
b00000000000000000000000000001010 '"
1/"
#4080
0/"
#4090
b0000000000010000 [
b00000000000000000000000000000101 '"
1/"
#4100
0/"
#4110
b0000000000010001 [
b00000000000000000000000000010000 '"
1/"
#4120
0/"
#4130
b0000000000010010 [
b00000000000000000000000000001000 '"
1/"
#4140
0/"
#4150
b0000000000010011 [
b00000000000000000000000000000100 '"
1/"
#4160
0/"
#4170
b0000000000010100 [
b00000000000000000000000000000010 '"
1/"
#4180
0/"
#4190
1;
b0000000000010101 [
b00000000000000000000000000000001 '"
1/"
#4200
0/"
#4210
b1101 +
13
1S
1/"
#4220
0/"
#4230
b0111 +
03
0;
b00000000000000000000000000010101 C
b1110 K
0S
b0000000000000001 [
b0000000000010101 p
b00000000000000000000000000010100 '"
1/"
b0000000000000000 O"
#4240
0/"
#4250
b0000000000000010 [
b00000000000000000000000000001010 '"
1/"
b0000000000001010 O"
#4260
0/"
#4270
b0000000000000011 [
b00000000000000000000000000000101 '"
1/"
#4280
0/"
#4290
b0000000000000100 [
b00000000000000000000000000010000 '"
1/"
#4300
0/"
#4310
b0000000000000101 [
b00000000000000000000000000001000 '"
1/"
#4320
0/"
#4330
b0000000000000110 [
b00000000000000000000000000000100 '"
1/"
#4340
0/"
#4350
b0000000000000111 [
b00000000000000000000000000000010 '"
1/"
#4360
0/"
#4370
1;
b0000000000001000 [
b00000000000000000000000000000001 '"
1/"
#4380
0/"
#4390
b1110 +
13
1S
1/"
#4400
0/"
#4410
b0111 +
03
0;
b00000000000000000000000000010110 C
b1111 K
0S
b0000000000000001 [
b0000000000001000 q
b00000000000000000000000000010101 '"
1/"
b0000000000000000 O"
#4420
0/"
#4430
b0000000000000010 [
b00000000000000000000000001000000 '"
1/"
b0000000000001010 O"
#4440
0/"
#4450
b0000000000000011 [
b00000000000000000000000000100000 '"
1/"
#4460
0/"
#4470
b0000000000000100 [
b00000000000000000000000000010000 '"
1/"
#4480
0/"
#4490
b0000000000000101 [
b00000000000000000000000000001000 '"
1/"
#4500
0/"
#4510
b0000000000000110 [
b00000000000000000000000000000100 '"
1/"
#4520
0/"
#4530
b0000000000000111 [
b00000000000000000000000000000010 '"
1/"
#4540
0/"
#4550
1;
b0000000000001000 [
b00000000000000000000000000000001 '"
1/"
#4560
0/"
#4570
b1111 +
13
1S
1/"
#4580
0/"
#4590
0#
b0111 +
03
0;
b00000000000000000000000000010111 C
b0000 K
0S
b0000000000000001 [
b0000000000001000 r
b00000000000000000000000000010110 '"
1/"
1G"
b0000000000000000 O"
#4600
b0000 +
0/"
b00000000000000000000000000000000 ?"
#4610
b00000000000000000000000000001011 '"
1/"
0G"
b0000000000010001 O"
#4620
b0001 +
0/"
b00000000000000000000000000000001 ?"
#4630
b00000000000000000000000000100010 '"
1/"
#4640
b0010 +
0/"
b00000000000000000000000000000010 ?"
#4650
b00000000000000000000000000010001 '"
1/"
b0000000000000100 O"
#4660
b0011 +
0/"
b00000000000000000000000000000011 ?"
#4670
b00000000000000000000000000110100 '"
1/"
b0000000000010100 O"
#4680
b0100 +
0/"
b00000000000000000000000000000100 ?"
#4690
b00000000000000000000000000011010 '"
1/"
b0000000000000111 O"
#4700
b0101 +
0/"
b00000000000000000000000000000101 ?"
#4710
b00000000000000000000000000001101 '"
1/"
b0000000000001111 O"
#4720
b0110 +
0/"
b00000000000000000000000000000110 ?"
#4730
b00000000000000000000000000101000 '"
1/"
b0000000000001010 O"
#4740
b0111 +
0/"
b00000000000000000000000000000111 ?"
#4750
b00000000000000000000000000010100 '"
1/"
#4760
b1000 +
0/"
b00000000000000000000000000001000 ?"
#4770
b00000000000000000000000000001010 '"
1/"
b0000000000010010 O"
#4780
b1001 +
0/"
b00000000000000000000000000001001 ?"
#4790
b00000000000000000000000000000101 '"
1/"
#4800
b1010 +
0/"
b00000000000000000000000000001010 ?"
#4810
b00000000000000000000000000010000 '"
1/"
b0000000000000101 O"
#4820
b1011 +
0/"
b00000000000000000000000000001011 ?"
#4830
b00000000000000000000000000001000 '"
1/"
b0000000000001101 O"
#4840
b1100 +
0/"
b00000000000000000000000000001100 ?"
#4850
b00000000000000000000000000000100 '"
1/"
b0000000000010101 O"
#4860
b1101 +
0/"
b00000000000000000000000000001101 ?"
#4870
b00000000000000000000000000000010 '"
1/"
#4880
b1110 +
0/"
b00000000000000000000000000001110 ?"
#4890
1;
b00000000000000000000000000000001 '"
1/"
b0000000000001000 O"
#4900
b1111 +
0/"
b00000000000000000000000000001111 ?"
#4910
b0000 +
13
1S
1/"
